odoo/addons/storage_backend_ftp/README.rst
odoo/addons/storage_backend_ftp/__init__.py
odoo/addons/storage_backend_ftp/__manifest__.py
odoo/addons/storage_backend_ftp/components/__init__.py
odoo/addons/storage_backend_ftp/components/ftp_adapter.py
odoo/addons/storage_backend_ftp/i18n/it.po
odoo/addons/storage_backend_ftp/i18n/storage_backend_ftp.pot
odoo/addons/storage_backend_ftp/models/__init__.py
odoo/addons/storage_backend_ftp/models/storage_backend.py
odoo/addons/storage_backend_ftp/readme/CONTRIBUTORS.md
odoo/addons/storage_backend_ftp/readme/CREDITS.md
odoo/addons/storage_backend_ftp/readme/DESCRIPTION.md
odoo/addons/storage_backend_ftp/static/description/icon.png
odoo/addons/storage_backend_ftp/static/description/index.html
odoo/addons/storage_backend_ftp/tests/__init__.py
odoo/addons/storage_backend_ftp/tests/test_ftp.py
odoo/addons/storage_backend_ftp/views/backend_storage_view.xml
odoo_addon_storage_backend_ftp-18.0.1.0.0.5.dist-info/METADATA
odoo_addon_storage_backend_ftp-18.0.1.0.0.5.dist-info/WHEEL
odoo_addon_storage_backend_ftp-18.0.1.0.0.5.dist-info/top_level.txt
odoo_addon_storage_backend_ftp-18.0.1.0.0.5.dist-info/RECORD
